odoo/addons/stock_storage_type/README.rst
odoo/addons/stock_storage_type/__init__.py
odoo/addons/stock_storage_type/__manifest__.py
odoo/addons/stock_storage_type/demo/product_packaging.xml
odoo/addons/stock_storage_type/demo/stock_location.xml
odoo/addons/stock_storage_type/demo/stock_location_storage_type.xml
odoo/addons/stock_storage_type/demo/stock_package_storage_type.xml
odoo/addons/stock_storage_type/demo/stock_storage_location_sequence.xml
odoo/addons/stock_storage_type/i18n/es_AR.po
odoo/addons/stock_storage_type/i18n/it.po
odoo/addons/stock_storage_type/i18n/stock_storage_type.pot
odoo/addons/stock_storage_type/models/__init__.py
odoo/addons/stock_storage_type/models/product_packaging.py
odoo/addons/stock_storage_type/models/product_template.py
odoo/addons/stock_storage_type/models/stock_location.py
odoo/addons/stock_storage_type/models/stock_location_package_storage_type_rel.py
odoo/addons/stock_storage_type/models/stock_location_storage_type.py
odoo/addons/stock_storage_type/models/stock_move.py
odoo/addons/stock_storage_type/models/stock_package_level.py
odoo/addons/stock_storage_type/models/stock_package_storage_type.py
odoo/addons/stock_storage_type/models/stock_quant.py
odoo/addons/stock_storage_type/models/stock_quant_package.py
odoo/addons/stock_storage_type/models/stock_storage_location_sequence.py
odoo/addons/stock_storage_type/models/stock_storage_location_sequence_cond.py
odoo/addons/stock_storage_type/readme/CONFIGURATION.rst
odoo/addons/stock_storage_type/readme/CONTRIBUTORS.rst
odoo/addons/stock_storage_type/readme/DESCRIPTION.rst
odoo/addons/stock_storage_type/readme/ROADMAP.rst
odoo/addons/stock_storage_type/security/ir.model.access.csv
odoo/addons/stock_storage_type/static/description/icon.png
odoo/addons/stock_storage_type/static/description/index.html
odoo/addons/stock_storage_type/tests/__init__.py
odoo/addons/stock_storage_type/tests/common.py
odoo/addons/stock_storage_type/tests/test_auto_assign_storage_type.py
odoo14_addon_stock_storage_type-14.0.1.12.2.dist-info/METADATA
odoo14_addon_stock_storage_type-14.0.1.12.2.dist-info/WHEEL
odoo14_addon_stock_storage_type-14.0.1.12.2.dist-info/top_level.txt
odoo14_addon_stock_storage_type-14.0.1.12.2.dist-info/RECORD
