Metadata-Version: 2.1
Name: odoo14-addon-stock-storage-type
Version: 14.0.1.12.2
Summary: Manage packages and locations storage types
Home-page: https://github.com/OCA/wms
Author: Camptocamp, BCIM, Odoo Community Association (OCA)
Author-email: support@odoo-community.org
License: AGPL-3
Platform: UNKNOWN
Classifier: Programming Language :: Python
Classifier: Framework :: Odoo
Classifier: Framework :: Odoo :: 14.0
Classifier: License :: OSI Approved :: GNU Affero General Public License v3
Classifier: Development Status :: 4 - Beta
Requires-Python: >=3.6
Requires-Dist: odoo14-addon-base-m2m-custom-field
Requires-Dist: odoo14-addon-stock-putaway-hook
Requires-Dist: odoo14-addon-stock-quant-package-dimension
Requires-Dist: odoo14-addon-web-domain-field
Requires-Dist: odoo <14.1dev,>=14.0a
